modx/__init__.py
modx/modx.py
modxpy-1.24.2.dist-info/METADATA
modxpy-1.24.2.dist-info/WHEEL
modxpy-1.24.2.dist-info/top_level.txt
modxpy-1.24.2.dist-info/RECORD
