Metadata-Version: 2.4
Name: modxpy
Version: 1.24.2
Summary: ModX — The Python Module Universe at Your Fingertips
Author: Austin Wang
Author-email: austinw87654@gmail.com
Requires-Python: >=3.8
Dynamic: author
Dynamic: author-email
Dynamic: description
Dynamic: description-content-type
Dynamic: requires-python
Dynamic: summary
